practice_total_game/__init__.py
practice_total_game/practice_total_game.py
practice_total_game-0.1.0.dist-info/LICENSE
practice_total_game-0.1.0.dist-info/METADATA
practice_total_game-0.1.0.dist-info/WHEEL
practice_total_game-0.1.0.dist-info/top_level.txt
practice_total_game-0.1.0.dist-info/RECORD
